varsubst/__init__.py
varsubst/exceptions.py
varsubst/resolvers.py
varsubst/interpolators/__init__.py
varsubst/interpolators/base_interpolator.py
varsubst/interpolators/jinja_interpolator.py
varsubst/interpolators/shell_interpolator.py
varsubst-2.0.0.dist-info/LICENSE
varsubst-2.0.0.dist-info/METADATA
varsubst-2.0.0.dist-info/WHEEL
varsubst-2.0.0.dist-info/top_level.txt
varsubst-2.0.0.dist-info/RECORD
