Metadata-Version: 2.1
Name: varsubst
Version: 2.0.0
Summary: Substitute variables in a string with a given resolver. Act as a render template.
Home-page: https://github.com/tiboun/varsubst
Author: Bounkong Khamphousone
Author-email: bounkong@gmail.com
License: MIT
Platform: UNKNOWN
Provides-Extra: jinja2
Requires-Dist: jinja2 ; extra == 'jinja2'
